MANIFEST.in
README
README.rst
setup.py
xzip/__init__.py
xzip/analyze.py
xzip/explode.py
xzip/fs.py
xzip.egg-info/PKG-INFO
xzip.egg-info/SOURCES.txt
xzip.egg-info/dependency_links.txt
xzip.egg-info/entry_points.txt
xzip.egg-info/requires.txt
xzip.egg-info/top_level.txt