Metadata-Version: 1.0
Name: xzip
Version: 0.10
Summary: E[x]ploded zip file system in FUSE
Home-page: https://github.com/terencehonles/xzip
Author: Terence Honles
Author-email: terence@honles.com
License: PSF
Keywords: FS FileSystem File System Zip Deduplication
Platform: UNKNOWN
Classifier: Development Status :: 4 - Beta
Classifier: Environment :: Console
Classifier: Intended Audience :: Information Technology
Classifier: Intended Audience :: System Administrators
Classifier: License :: OSI Approved :: Python Software Foundation License
Classifier: Operating System :: MacOS
Classifier: Operating System :: POSIX
Classifier: Operating System :: Unix
Classifier: Programming Language :: Python :: 2
Classifier: Programming Language :: Python :: 3
Classifier: Topic :: System :: Filesystems
